{
  "background": "EEE6CE",
  "materials": [
    {
      "id": 0,
      "name": "Sand",
      "color": "2EB086",
      "key": "Key1",
      "rules": [
        {
          "movement": {
            "Move": {
              "row": 1,
              "column": 0
            }
          },
          "if_empty": [
            {
              "row": 1,
              "column": 0
            }
          ],
          "if_occupied": []
        },
        {
          "movement": {
            "Move": {
              "row": 1,
              "column": -1
            }
          },
          "if_empty": [
            {
              "row": 1,
              "column": -1
            }
          ],
          "if_occupied": []
        },
        {
          "movement": {
            "Move": {
              "row": 1,
              "column": 1
            }
          },
          "if_empty": [
            {
              "row": 1,
              "column": 1
            }
          ],
          "if_occupied": []
        }
      ]
    },
    {
      "id": 1,
      "name": "Water",
      "color": "2666CF",
      "key": "Key2",
      "rules": [
        {
          "movement": {
            "Move": {
              "row": 1,
              "column": 0
            }
          },
          "if_empty": [
            {
              "row": 1,
              "column": 0
            }
          ],
          "if_occupied": []
        },
        {
          "movement": {
            "Move": {
              "row": 1,
              "column": -1
            }
          },
          "if_empty": [
            {
              "row": 1,
              "column": -1
            }
          ],
          "if_occupied": []
        },
        {
          "movement": {
            "Move": {
              "row": 1,
              "column": 1
            }
          },
          "if_empty": [
            {
              "row": 1,
              "column": 1
            }
          ],
          "if_occupied": []
        },
        {
          "movement": {
            "Move": {
              "row": 1,
              "column": -2
            }
          },
          "if_empty": [
            {
              "row": 1,
              "column": -2
            }
          ],
          "if_occupied": []
        },
        {
          "movement": {
            "Move": {
              "row": 1,
              "column": 2
            }
          },
          "if_empty": [
            {
              "row": 1,
              "column": 2
            }
          ],
          "if_occupied": []
        },
        {
          "movement": {
            "Move": {
              "row": 1,
              "column": -3
            }
          },
          "if_empty": [
            {
              "row": 1,
              "column": -3
            }
          ],
          "if_occupied": []
        },
        {
          "movement": {
            "Move": {
              "row": 1,
              "column": 3
            }
          },
          "if_empty": [
            {
              "row": 1,
              "column": 3
            }
          ],
          "if_occupied": []
        },
        {
          "movement": {
            "Move": {
              "row": 0,
              "column": -1
            }
          },
          "if_empty": [
            {
              "row": 0,
              "column": -1
            }
          ],
          "if_occupied": []
        },
        {
          "movement": {
            "Move": {
              "row": 0,
              "column": 1
            }
          },
          "if_empty": [
            {
              "row": 0,
              "column": 1
            }
          ],
          "if_occupied": []
        }
      ]
    },
    {
      "id": 2,
      "name": "Wall",
      "color": "B8405E",
      "key": "Key3",
      "rules": []
    },
    {
      "id": 3,
      "name": "Plague",
      "color": "8A39E1",
      "key": "Key4",
      "rules": [
        {
          "movement": {
            "Move": {
              "row": 1,
              "column": 0
            }
          },
          "if_empty": [
            {
              "row": 1,
              "column": 0
            }
          ],
          "if_occupied": []
        },
        {
          "movement": {
            "Move": {
              "row": 1,
              "column": -1
            }
          },
          "if_empty": [
            {
              "row": 1,
              "column": -1
            }
          ],
          "if_occupied": []
        },
        {
          "movement": {
            "Move": {
              "row": 1,
              "column": 1
            }
          },
          "if_empty": [
            {
              "row": 1,
              "column": 1
            }
          ],
          "if_occupied": []
        },
        {
          "movement": {
            "Copy": {
              "row": 0,
              "column": -1
            }
          },
          "if_empty": [],
          "if_occupied": [
            {
              "row": 0,
              "column": -1
            }
          ]
        },
        {
          "movement": {
            "Copy": {
              "row": 0,
              "column": 1
            }
          },
          "if_empty": [],
          "if_occupied": [
            {
              "row": 0,
              "column": 1
            }
          ]
        },
        {
          "movement": {
            "Copy": {
              "row": -1,
              "column": 0
            }
          },
          "if_empty": [],
          "if_occupied": [
            {
              "row": -1,
              "column": 0
            }
          ]
        },
        {
          "movement": {
            "Copy": {
              "row": -1,
              "column": -1
            }
          },
          "if_empty": [],
          "if_occupied": [
            {
              "row": -1,
              "column": -1
            }
          ]
        },
        {
          "movement": {
            "Copy": {
              "row": -1,
              "column": 1
            }
          },
          "if_empty": [],
          "if_occupied": [
            {
              "row": -1,
              "column": 1
            }
          ]
        },
        {
          "movement": {
            "Copy": {
              "row": 1,
              "column": 0
            }
          },
          "if_empty": [],
          "if_occupied": [
            {
              "row": 1,
              "column": 0
            }
          ]
        },
        {
          "movement": {
            "Copy": {
              "row": 1,
              "column": -1
            }
          },
          "if_empty": [],
          "if_occupied": [
            {
              "row": 1,
              "column": -1
            }
          ]
        },
        {
          "movement": {
            "Copy": {
              "row": 1,
              "column": 1
            }
          },
          "if_empty": [],
          "if_occupied": [
            {
              "row": 1,
              "column": 1
            }
          ]
        }
      ]
    },
    {
      "id": 4,
      "name": "Acidic sand",
      "color": "F76E11",
      "key": "Key5",
      "rules": [
        {
          "movement": {
            "Move": {
              "row": 1,
              "column": 0
            }
          },
          "if_empty": [
            {
              "row": 1,
              "column": 0
            }
          ],
          "if_occupied": []
        },
        {
          "movement": {
            "Move": {
              "row": 1,
              "column": -1
            }
          },
          "if_empty": [
            {
              "row": 1,
              "column": -1
            }
          ],
          "if_occupied": []
        },
        {
          "movement": {
            "Move": {
              "row": 1,
              "column": 1
            }
          },
          "if_empty": [
            {
              "row": 1,
              "column": 1
            }
          ],
          "if_occupied": []
        },
        {
          "movement": {
            "Move": {
              "row": 1,
              "column": 0
            }
          },
          "if_empty": [],
          "if_occupied": [
            {
              "row": 1,
              "column": 0
            }
          ]
        },
        {
          "movement": {
            "Move": {
              "row": 1,
              "column": -1
            }
          },
          "if_empty": [],
          "if_occupied": [
            {
              "row": 1,
              "column": -1
            }
          ]
        },
        {
          "movement": {
            "Move": {
              "row": 1,
              "column": 1
            }
          },
          "if_empty": [],
          "if_occupied": [
            {
              "row": 1,
              "column": 1
            }
          ]
        },
        {
          "movement": {
            "Move": {
              "row": -1,
              "column": 0
            }
          },
          "if_empty": [],
          "if_occupied": [
            {
              "row": -1,
              "column": 0
            }
          ]
        },
        {
          "movement": {
            "Move": {
              "row": -1,
              "column": -1
            }
          },
          "if_empty": [],
          "if_occupied": [
            {
              "row": -1,
              "column": -1
            }
          ]
        },
        {
          "movement": {
            "Move": {
              "row": -1,
              "column": 1
            }
          },
          "if_empty": [],
          "if_occupied": [
            {
              "row": -1,
              "column": 1
            }
          ]
        },
        {
          "movement": {
            "Move": {
              "row": 0,
              "column": -1
            }
          },
          "if_empty": [],
          "if_occupied": [
            {
              "row": 0,
              "column": -1
            }
          ]
        },
        {
          "movement": {
            "Move": {
              "row": 0,
              "column": 1
            }
          },
          "if_empty": [],
          "if_occupied": [
            {
              "row": 0,
              "column": 1
            }
          ]
        }
      ]
    }
  ]
}
